tirjapy/base/HandleConstants.py
tirjapy/base/StoreBase.py
tirjapy/base/WebServiceBase.py
tirjapy/utils/CalyrexHandle.py
tirjapy/utils/FileStoreBase.py
tirjapy/utils/HandleQuotes.py
tirjapy/utils/HtPasswdAuth.py
tirjapy/utils/HttpPostHandle.py
tirjapy/utils/JcsvData.py
tirjapy/utils/MysqlHandleBase.py
tirjapy/utils/Porygon.py
tirjapy/utils/RazorpayHandle.py
tirjapy/utils/StorageHandle.py
tirjapy/utils/TypedEnum.py
tirjapy-1.1.2.dist-info/licenses/LICENSE.txt
tirjapy-1.1.2.dist-info/METADATA
tirjapy-1.1.2.dist-info/WHEEL
tirjapy-1.1.2.dist-info/top_level.txt
tirjapy-1.1.2.dist-info/RECORD
