Metadata-Version: 2.4
Name: tirjapy
Version: 1.1.2
Summary: python common tools
Author-email: Shreos Roychowdhury <shreos@tirja.com>
Classifier: Development Status :: 3 - Alpha
Classifier: Programming Language :: Python :: 3
Classifier: Programming Language :: Python :: 3.10
Classifier: Programming Language :: Python :: 3.11
Classifier: Programming Language :: Python :: 3.12
Classifier: Intended Audience :: Developers
Classifier: Natural Language :: English
Requires-Python: >=3.10
License-File: LICENSE.txt
Requires-Dist: passlib>=1.7.4
Requires-Dist: requests>=2.32.3
Requires-Dist: mysql-connector-python>=9.1.0
Requires-Dist: bitsets>=0.8.4
Requires-Dist: pycryptodome>=3.21.0
Requires-Dist: boto3>=1.35.92
Requires-Dist: loguru>=0.7.3
Dynamic: license-file
